RequestPackat/__init__.py
requestpackat-1.0.2.dist-info/METADATA
requestpackat-1.0.2.dist-info/WHEEL
requestpackat-1.0.2.dist-info/top_level.txt
requestpackat-1.0.2.dist-info/RECORD
