Metadata-Version: 2.4
Name: RequestPackat
Version: 1.0.2
Summary: Run Packat
Author: Packed
Author-email: oelfaesraali@gmail.com
Classifier: Programming Language :: Python :: 3
Classifier: Operating System :: Microsoft :: Windows
Requires-Python: >=3.6
Requires-Dist: requests
Dynamic: author
Dynamic: author-email
Dynamic: classifier
Dynamic: requires-dist
Dynamic: requires-python
Dynamic: summary
